tbuild/__init__.py
tbuild-1.0.0.dist-info/METADATA
tbuild-1.0.0.dist-info/WHEEL
tbuild-1.0.0.dist-info/entry_points.txt
tbuild-1.0.0.dist-info/top_level.txt
tbuild-1.0.0.dist-info/RECORD
