Metadata-Version: 2.1
Name: tbuild
Version: 1.0.0
Summary: It is the build system of SafeOS, which is based on Conan
Author-email: "Zhiguo.Zhu" <294966@qq.com>
Requires-Python: <3.12,>=3.8
Requires-Dist: conan<2.0.0,>=1.59.0
Requires-Dist: dockerpty==0.4.1
Requires-Dist: docker==7.1.0
Requires-Dist: intervaltree==3.1.0
Requires-Dist: pyelftools==0.29
Requires-Dist: ruamel.yaml==0.17.21
Requires-Dist: psutil==5.9.4
Requires-Dist: pyserial==3.5
Requires-Dist: fbtftp==0.5
Requires-Dist: dohq-artifactory==0.8.4
Requires-Dist: aiohttp==3.8.4
Requires-Dist: easy-enum==0.3.0
